papdl/__init__.py
papdl/backend/__init__.py
papdl/backend/_api_benchmark.py
papdl/backend/_api_deploy.py
papdl/backend/_api_iperf.py
papdl/backend/_api_registry.py
papdl/backend/_api_slice.py
papdl/backend/api.py
papdl/backend/api_common.py
papdl/backend/certificates/.stub
papdl/backend/common.py
papdl/backend/containers/Benchmarker/Dockerfile
papdl/backend/containers/Benchmarker/app/server.py
papdl/backend/containers/Benchmarker/requirements.txt
papdl/backend/containers/Orchestrator/Dockerfile
papdl/backend/containers/Orchestrator/app/__init__.py
papdl/backend/containers/Orchestrator/app/configure.py
papdl/backend/containers/Orchestrator/app/iss_message.proto
papdl/backend/containers/Orchestrator/app/proto/__init__.py
papdl/backend/containers/Orchestrator/app/proto/iss_message_pb2.py
papdl/backend/containers/Orchestrator/app/server.py
papdl/backend/containers/Orchestrator/app/wsc.py
papdl/backend/containers/Orchestrator/requirements.txt
papdl/backend/containers/Slice/Dockerfile
papdl/backend/containers/Slice/app/iss_message.proto
papdl/backend/containers/Slice/app/proto/__init__.py
papdl/backend/containers/Slice/app/proto/iss_message_pb2.py
papdl/backend/containers/Slice/app/server.py
papdl/backend/containers/Slice/requirements.txt
papdl/backend/registry_volume/.stub
papdl/benchmark/__init__.py
papdl/benchmark/benchmark.py
papdl/benchmark/main.py
papdl/benchmark/network_statistics.csv
papdl/benchmark/temp.py
papdl/clean/__init__.py
papdl/clean/main.py
papdl/cli.py
papdl/configure/__init__.py
papdl/configure/configure.py
papdl/configure/main.py
papdl/deploy/deploy.py
papdl/deploy/main.py
papdl/slice/__init__.py
papdl/slice/main.py
papdl/slice/slice.py
papdl-0.1.2.dist-info/METADATA
papdl-0.1.2.dist-info/WHEEL
papdl-0.1.2.dist-info/entry_points.txt
papdl-0.1.2.dist-info/RECORD
